respan_exporter_litellm/__init__.py
respan_exporter_litellm/exporter.py
respan_exporter_litellm-1.0.0.dist-info/METADATA
respan_exporter_litellm-1.0.0.dist-info/WHEEL
respan_exporter_litellm-1.0.0.dist-info/RECORD
