Metadata-Version: 2.1
Name: respan-exporter-litellm
Version: 1.0.0
Summary: Respan exporter for LiteLLM
Author: Respan
Author-email: team@respan.ai
Requires-Python: >=3.12,<4.0
Classifier: Programming Language :: Python :: 3
Classifier: Programming Language :: Python :: 3.12
Requires-Dist: requests (>=2.32.5,<3.0.0)
